src/__init__.py
src/app.py
src/plugins/1password.py
src/plugins/__init__.py
src/plugins/bitwarden.py
src/plugins/pass.py
temv-0.1.0.dist-info/LICENSE
temv-0.1.0.dist-info/METADATA
temv-0.1.0.dist-info/WHEEL
temv-0.1.0.dist-info/entry_points.txt
temv-0.1.0.dist-info/RECORD
