Metadata-Version: 2.3
Name: temv
Version: 0.1.0
Summary: A tool for templating .env files.
Keywords: template,management,jinja2,secrets,dotenv,.env
Author: Ben Trinh
Author-email: huantrinh1802@gmail.com
Requires-Python: >=3.12,<4.0
Classifier: Programming Language :: Python :: 3
Classifier: Programming Language :: Python :: 3.12
Classifier: Programming Language :: Python :: 3.13
Requires-Dist: jinja2 (>=3.1.5,<4.0.0)
Project-URL: Homepage, https://github.com/huantrinh1802/temv
Project-URL: Issues, https://github.com/huantrinh1802/temv/issues
